{"cameraMode":{"drawMode":0,"name":"Shaded","section":"Shading Mode"},"sceneLighting":false,"audioPlay":false,"sceneViewState":{"m_AlwaysRefresh":false,"showFog":true,"showSkybox":false,"showFlares":true,"showImageEffects":true,"showParticleSystems":true,"showVisualEffectGraphs":true,"m_FxEnabled":true},"in2DMode":false,"pivot":{"x":-6.512510299682617,"y":0.6716928482055664,"z":-0.9231579303741455},"rotation":{"x":0.5308770537376404,"y":-0.2330654263496399,"z":0.15466953814029694,"w":0.799956202507019},"size":3.096355438232422,"orthographic":false}